[
  {
    "Name": "B-Seminar_C",
    "Location": "0560",
    "Description": "Dozent: LMN",
    "StartTime": "2024-04-08T16:00:00+02:00",
    "EndTime": "2024-04-08T18:00:00+02:00"
  },
  {
    "Name": "B-Seminar_C",
    "Location": "0560",
    "Description": "Dozent: LMN",
    "StartTime": "2024-04-15T16:00:00+02:00",
    "EndTime": "2024-04-15T18:00:00+02:00"
  },
  {
    "Name": "B-Seminar_C",
    "Location": "0560",
    "Description": "Dozent: LMN",
    "StartTime": "2024-04-22T16:00:00+02:00",
    "EndTime": "2024-04-22T18:00:00+02:00"
  },
  {
    "Name": "B-Seminar_C",
    "Location": "0560",
    "Description": "Dozent: LMN",
    "StartTime": "2024-04-29T16:00:00+02:00",
    "EndTime": "2024-04-29T18:00:00+02:00"
  },
  {
    "Name": "B-Seminar_C",
    "Location": "0560",
    "Description": "Dozent: LMN",
    "StartTime": "2024-05-06T16:00:00+02:00",
    "EndTime": "2024-05-06T18:00:00+02:00"
  },
  {
    "Name": "B-Seminar_C",
    "Location": "0560",
    "Description": "Dozent: LMN",
    "StartTime": "2024-05-13T16:00:00+02:00",
    "EndTime": "2024-05-13T18:00:00+02:00"
  },
  {
    "Name": "B-Seminar_C",
    "Location": "0560",
    "Description": "Dozent: LMN",
    "StartTime": "2024-05-21T16:00:00+02:00",
    "EndTime": "2024-05-21T18:00:00+02:00"
  },
  {
    "Name": "B-Seminar_C",
    "Location": "0560",
    "Description": "Dozent: LMN",
    "StartTime": "2024-05-27T16:00:00+02:00",
    "EndTime": "2024-05-27T18:00:00+02:00"
  },
  {
    "Name": "B-Seminar_C",
    "Location": "0560",
    "Description": "Dozent: LMN",
    "StartTime": "2024-06-03T16:00:00+02:00",
    "EndTime": "2024-06-03T18:00:00+02:00"
  },
  {
    "Name": "B-Seminar_C",
    "Location": "0560",
    "Description": "Dozent: LMN",
    "StartTime": "2024-06-10T16:00:00+02:00",
    "EndTime": "2024-06-10T18:00:00+02:00"
  },
  {
    "Name": "B-Seminar_C",
    "Location": "0560",
    "Description": "Dozent: LMN",
    "StartTime": "2024-06-17T16:00:00+02:00",
    "EndTime": "2024-06-17T18:00:00+02:00"
  },
  {
    "Name": "B-Seminar_C",
    "Location": "0560",
    "Description": "Dozent: LMN",
    "StartTime": "2024-06-24T16:00:00+02:00",
    "EndTime": "2024-06-24T18:00:00+02:00"
  },
  {
    "Name": "B-Seminar_C",
    "Location": "0560",
    "Description": "Dozent: LMN",
    "StartTime": "2024-07-01T16:00:00+02:00",
    "EndTime": "2024-07-01T18:00:00+02:00"
  },
  {
    "Name": "B-Seminar_C",
    "Location": "0560",
    "Description": "Dozent: LMN",
    "StartTime": "2024-07-08T16:00:00+02:00",
    "EndTime": "2024-07-08T18:00:00+02:00"
  }
]