[
  {
    "Name": "BITS2-DBP/02",
    "Location": "0380b",
    "Description": "Dozent: HMN/[Bro]",
    "StartTime": "2023-03-27T08:15:00+02:00",
    "EndTime": "2023-03-27T09:45:00+02:00"
  },
  {
    "Name": "BITS2-DBP/02",
    "Location": "0380b",
    "Description": "Dozent: HMN/[Bro]",
    "StartTime": "2023-04-17T08:15:00+02:00",
    "EndTime": "2023-04-17T09:45:00+02:00"
  },
  {
    "Name": "BITS2-DBP/02",
    "Location": "0380b",
    "Description": "Dozent: HMN/[Bro]",
    "StartTime": "2023-05-03T08:15:00+02:00",
    "EndTime": "2023-05-03T09:45:00+02:00"
  },
  {
    "Name": "BITS2-DBP/02",
    "Location": "0380b",
    "Description": "Dozent: HMN/[Bro]",
    "StartTime": "2023-05-15T08:15:00+02:00",
    "EndTime": "2023-05-15T09:45:00+02:00"
  },
  {
    "Name": "BITS2-DBP/02",
    "Location": "0380b",
    "Description": "Dozent: HMN/[Bro]",
    "StartTime": "2023-05-30T08:15:00+02:00",
    "EndTime": "2023-05-30T09:45:00+02:00"
  },
  {
    "Name": "BITS2-DBP/02",
    "Location": "0380b",
    "Description": "Dozent: HMN/[Bro]",
    "StartTime": "2023-06-12T08:15:00+02:00",
    "EndTime": "2023-06-12T09:45:00+02:00"
  },
  {
    "Name": "BITS2-DBP/02",
    "Location": "0380b",
    "Description": "Dozent: HMN/[Bro]",
    "StartTime": "2023-06-26T08:15:00+02:00",
    "EndTime": "2023-06-26T09:45:00+02:00"
  }
]