[
  {
    "Name": "BITS6-CPSP/02",
    "Location": "",
    "Description": "Dozent: SKT/[Mat]",
    "StartTime": "2024-04-25T08:15:00+02:00",
    "EndTime": "2024-04-25T11:30:00+02:00"
  },
  {
    "Name": "BITS6-CPSP/02",
    "Location": "",
    "Description": "Dozent: SKT/[Mat]",
    "StartTime": "2024-05-23T08:15:00+02:00",
    "EndTime": "2024-05-23T11:30:00+02:00"
  },
  {
    "Name": "BITS6-CPSP/02",
    "Location": "",
    "Description": "Dozent: SKT/[Mat]",
    "StartTime": "2024-06-13T08:15:00+02:00",
    "EndTime": "2024-06-13T11:30:00+02:00"
  },
  {
    "Name": "BITS6-CPSP/02",
    "Location": "",
    "Description": "Dozent: SKT/[Mat]",
    "StartTime": "2024-07-04T08:15:00+02:00",
    "EndTime": "2024-07-04T11:30:00+02:00"
  }
]