[
  {
    "Name": "E3-OPP-02",
    "Location": "1301a, 1301b",
    "Description": "Dozent: DRK",
    "StartTime": "2024-10-30T12:10:00+01:00",
    "EndTime": "2024-10-30T15:40:00+01:00"
  },
  {
    "Name": "E3-OPP-02",
    "Location": "1360",
    "Description": "Dozent: DRK",
    "StartTime": "2024-11-21T08:10:00+01:00",
    "EndTime": "2024-11-21T11:25:00+01:00"
  },
  {
    "Name": "E3-OPP-02",
    "Location": "1360",
    "Description": "Dozent: DRK",
    "StartTime": "2024-12-12T08:10:00+01:00",
    "EndTime": "2024-12-12T11:25:00+01:00"
  },
  {
    "Name": "E3-OPP-02",
    "Location": "1360",
    "Description": "Dozent: DRK",
    "StartTime": "2025-01-16T08:10:00+01:00",
    "EndTime": "2025-01-16T11:25:00+01:00"
  }
]