[
  {
    "Name": "E4-GNP/02 opt",
    "Location": "1401",
    "Description": "Dozent: LI/NGBR",
    "StartTime": "2022-10-19T12:10:00+02:00",
    "EndTime": "2022-10-19T15:40:00+02:00"
  },
  {
    "Name": "E4-GNP/02 opt",
    "Location": "1401",
    "Description": "Dozent: LI/NGBR",
    "StartTime": "2022-11-09T12:10:00+01:00",
    "EndTime": "2022-11-09T15:40:00+01:00"
  },
  {
    "Name": "E4-GNP/02 opt",
    "Location": "1401",
    "Description": "Dozent: SHN/NGBR",
    "StartTime": "2022-11-30T12:10:00+01:00",
    "EndTime": "2022-11-30T15:40:00+01:00"
  },
  {
    "Name": "E4-GNP/02 opt",
    "Location": "1401",
    "Description": "Dozent: SHN/NGBR",
    "StartTime": "2022-12-21T12:10:00+01:00",
    "EndTime": "2022-12-21T15:40:00+01:00"
  }
]