[
  {
    "Name": "E6-RY",
    "Location": "SteinD94 R0.02",
    "Description": "Dozent: MAA",
    "StartTime": "2024-10-08T08:10:00+02:00",
    "EndTime": "2024-10-08T11:25:00+02:00"
  },
  {
    "Name": "E6-RY",
    "Location": "SteinD94 R0.02",
    "Description": "Dozent: MAA",
    "StartTime": "2024-10-15T08:10:00+02:00",
    "EndTime": "2024-10-15T11:25:00+02:00"
  },
  {
    "Name": "E6-RY",
    "Location": "SteinD94 R0.02",
    "Description": "Dozent: MAA",
    "StartTime": "2024-10-22T08:10:00+02:00",
    "EndTime": "2024-10-22T11:25:00+02:00"
  },
  {
    "Name": "E6-RY",
    "Location": "SteinD94 R0.02",
    "Description": "Dozent: MAA",
    "StartTime": "2024-10-29T08:10:00+01:00",
    "EndTime": "2024-10-29T11:25:00+01:00"
  },
  {
    "Name": "E6-RY",
    "Location": "SteinD94 R0.02",
    "Description": "Dozent: MAA",
    "StartTime": "2024-11-05T08:10:00+01:00",
    "EndTime": "2024-11-05T11:25:00+01:00"
  },
  {
    "Name": "E6-RY",
    "Location": "SteinD94 R0.02",
    "Description": "Dozent: MAA",
    "StartTime": "2024-11-12T08:10:00+01:00",
    "EndTime": "2024-11-12T11:25:00+01:00"
  },
  {
    "Name": "E6-RY",
    "Location": "SteinD94 R0.02",
    "Description": "Dozent: MAA",
    "StartTime": "2024-11-26T08:10:00+01:00",
    "EndTime": "2024-11-26T11:25:00+01:00"
  },
  {
    "Name": "E6-RY",
    "Location": "SteinD94 R0.02",
    "Description": "Dozent: MAA",
    "StartTime": "2024-12-03T08:10:00+01:00",
    "EndTime": "2024-12-03T11:25:00+01:00"
  },
  {
    "Name": "E6-RY",
    "Location": "SteinD94 R0.02",
    "Description": "Dozent: MAA",
    "StartTime": "2024-12-17T08:10:00+01:00",
    "EndTime": "2024-12-17T11:25:00+01:00"
  },
  {
    "Name": "E6-RY",
    "Location": "SteinD94 R0.02",
    "Description": "Dozent: MAA",
    "StartTime": "2025-01-07T08:10:00+01:00",
    "EndTime": "2025-01-07T11:25:00+01:00"
  },
  {
    "Name": "E6-RY",
    "Location": "SteinD94 R0.02",
    "Description": "Dozent: MAA",
    "StartTime": "2025-01-21T08:10:00+01:00",
    "EndTime": "2025-01-21T11:25:00+01:00"
  }
]