[
  {
    "Name": "E6-ZTP/01",
    "Location": "0601",
    "Description": "Dozent: WNC/EBEL",
    "StartTime": "2023-05-10T12:10:00+02:00",
    "EndTime": "2023-05-10T15:40:00+02:00"
  },
  {
    "Name": "E6-ZTP/01",
    "Location": "0601",
    "Description": "Dozent: WNC/EBEL",
    "StartTime": "2023-05-31T12:10:00+02:00",
    "EndTime": "2023-05-31T15:40:00+02:00"
  },
  {
    "Name": "E6-ZTP/01",
    "Location": "0601",
    "Description": "Dozent: WNC",
    "StartTime": "2023-06-15T08:10:00+02:00",
    "EndTime": "2023-06-15T11:25:00+02:00"
  },
  {
    "Name": "E6-ZTP/01",
    "Location": "0601",
    "Description": "Dozent: WNC/EBEL",
    "StartTime": "2023-06-21T12:10:00+02:00",
    "EndTime": "2023-06-21T15:40:00+02:00"
  }
]