[
  {
    "Name": "SHC-LE",
    "Location": "1265",
    "Description": "Dozent: GNZ",
    "StartTime": "2023-10-10T12:10:00+02:00",
    "EndTime": "2023-10-10T15:40:00+02:00"
  },
  {
    "Name": "SHC-LE",
    "Location": "1065",
    "Description": "Dozent: GNZ",
    "StartTime": "2023-10-11T08:10:00+02:00",
    "EndTime": "2023-10-11T11:25:00+02:00"
  },
  {
    "Name": "SHC-LE",
    "Location": "1265",
    "Description": "Dozent: GNZ",
    "StartTime": "2023-10-17T12:10:00+02:00",
    "EndTime": "2023-10-17T15:40:00+02:00"
  },
  {
    "Name": "SHC-LE",
    "Location": "1065",
    "Description": "Dozent: GNZ",
    "StartTime": "2023-10-18T08:10:00+02:00",
    "EndTime": "2023-10-18T11:25:00+02:00"
  },
  {
    "Name": "SHC-LE",
    "Location": "1265",
    "Description": "Dozent: GNZ",
    "StartTime": "2023-10-24T12:10:00+02:00",
    "EndTime": "2023-10-24T15:40:00+02:00"
  },
  {
    "Name": "SHC-LE",
    "Location": "1065",
    "Description": "Dozent: GNZ",
    "StartTime": "2023-10-25T08:10:00+02:00",
    "EndTime": "2023-10-25T11:25:00+02:00"
  },
  {
    "Name": "SHC-LE",
    "Location": "0862",
    "Description": "Dozent: GNZ",
    "StartTime": "2023-10-26T08:10:00+02:00",
    "EndTime": "2023-10-26T11:25:00+02:00"
  },
  {
    "Name": "SHC-LE",
    "Location": "1065",
    "Description": "Dozent: GNZ",
    "StartTime": "2023-11-01T08:10:00+01:00",
    "EndTime": "2023-11-01T11:25:00+01:00"
  },
  {
    "Name": "SHC-LE",
    "Location": "1265",
    "Description": "Dozent: GNZ",
    "StartTime": "2023-11-07T12:10:00+01:00",
    "EndTime": "2023-11-07T15:40:00+01:00"
  },
  {
    "Name": "SHC-LE",
    "Location": "1065",
    "Description": "Dozent: GNZ",
    "StartTime": "2023-11-08T08:10:00+01:00",
    "EndTime": "2023-11-08T11:25:00+01:00"
  },
  {
    "Name": "SHC-LE",
    "Location": "1065",
    "Description": "Dozent: GNZ",
    "StartTime": "2023-11-15T08:10:00+01:00",
    "EndTime": "2023-11-15T11:25:00+01:00"
  },
  {
    "Name": "SHC-LE",
    "Location": "1265",
    "Description": "Dozent: GNZ",
    "StartTime": "2023-11-21T12:10:00+01:00",
    "EndTime": "2023-11-21T15:40:00+01:00"
  }
]